README.md
setup.py
llb3d/__init__.py
llb3d/__main__.py
llb3d/ast.py
llb3d/backend.py
llb3d/context.py
llb3d/lexer.py
llb3d/parser.py
llb3d/parsetab.py
llb3d/version.py
llb3d.egg-info/PKG-INFO
llb3d.egg-info/SOURCES.txt
llb3d.egg-info/dependency_links.txt
llb3d.egg-info/entry_points.txt
llb3d.egg-info/not-zip-safe
llb3d.egg-info/requires.txt
llb3d.egg-info/top_level.txt
llb3d/tests/__init__.py
llb3d/tests/test_ast.py
llb3d/tests/test_backend.py
llb3d/tests/test_context.py
llb3d/tests/test_lexer.py
llb3d/tests/test_parser.py